{
  "name": "Anne+ Season 1",
  "part": "ANNE0101",
  "lesson": 24,
  "language": "nl",
  "words": [
    {
      "word": "dacht",
      "word_translated": "thought",
      "sentence": "Hij dacht dat het goed was.",
      "sentence_translated": "He thought it was good."
    },
    {
      "word": "schrijft",
      "word_translated": "writes",
      "sentence": "Zij schrijft een brief en dacht eraan.",
      "sentence_translated": "She writes a letter and thought about it."
    },
    {
      "word": "muziek",
      "word_translated": "music",
      "sentence": "Hij schrijft muziek en houdt ervan.",
      "sentence_translated": "He writes music and likes it."
    },
    {
      "word": "orinteren",
      "word_translated": "",
      "sentence": "",
      "sentence_translated": ""
    },
    {
      "word": "rustige",
      "word_translated": "calm",
      "sentence": "De rustige muziek helpt hem te ontspannen.",
      "sentence_translated": "The calm music helps him relax."
    },
    {
      "word": "bang",
      "word_translated": "afraid",
      "sentence": "Hij is bang voor de stilte na de muziek.",
      "sentence_translated": "He is afraid of the silence after the music."
    },
    {
      "word": "veel",
      "word_translated": "much/many",
      "sentence": "Ze heeft veel rustige muziek in haar bibliotheek.",
      "sentence_translated": "She has much calm music in her library."
    },
    {
      "word": "welke",
      "word_translated": "which",
      "sentence": "Welke muziek schrijft hij nu?",
      "sentence_translated": "Which music is he writing now?"
    },
    {
      "word": "mmm",
      "word_translated": "(sound of contemplation)",
      "sentence": "Hij zegt 'mmm' en dacht verder.",
      "sentence_translated": "He says 'mmm' and thought further."
    },
    {
      "word": "verbonden",
      "word_translated": "connected",
      "sentence": "De muziek is met zijn gedachten verbonden.",
      "sentence_translated": "The music is connected to his thoughts."
    }
  ]
}